solace_ai_connector_rest/__init__.py
solace_ai_connector_rest/components/__init__.py
solace_ai_connector_rest/components/openai_handlers.py
solace_ai_connector_rest/components/rest_base.py
solace_ai_connector_rest/components/rest_input.py
solace_ai_connector_rest/components/rest_output.py
solace_ai_connector_rest/components/utils.py
solace_ai_connector_rest-0.0.3.dist-info/METADATA
solace_ai_connector_rest-0.0.3.dist-info/WHEEL
solace_ai_connector_rest-0.0.3.dist-info/licenses/LICENSE
solace_ai_connector_rest-0.0.3.dist-info/RECORD
